[{
	"group": "Gym Leader",
	"trainer": "Janine",
	"unknown1": "0xab",
	"text": "text/gymleadercastle/kanto/janine2.txt",
	"pokemon": [{
		"level": 50,
		"species": "Crobat",
		"item": "King's Rock",
		"move1": "Confuse Ray",
		"move2": "Mean Look",
		"move3": "Toxic",
		"move4": "Bite",
		"unknown2": "0xf3",
		"unknown3": "0xff",
		"hp exp": "0xd200",
		"attack exp": "0xd200",
		"defense exp": "0xd200",
		"speed exp": "0xd200",
		"special exp": "0xd200",
		"dvs": "0x8c7c"
	},{
		"level": 50,
		"species": "Meganium",
		"item": "Quick Claw",
		"move1": "Attract",
		"move2": "Toxic",
		"move3": "Leech Seed",
		"move4": "Razor Leaf",
		"unknown2": "0x3",
		"unknown3": "0x80",
		"hp exp": "0xbe00",
		"attack exp": "0xbe00",
		"defense exp": "0xbe00",
		"speed exp": "0xbe00",
		"special exp": "0xbe00",
		"dvs": "0x7c7c"
	},{
		"level": 50,
		"species": "Muk",
		"item": "Focus Band",
		"move1": "Swagger",
		"move2": "Mean Look",
		"move3": "Toxic",
		"move4": "Fire Punch",
		"unknown2": "0xf3",
		"unknown3": "0x80",
		"hp exp": "0xbe00",
		"attack exp": "0xbe00",
		"defense exp": "0xbe00",
		"speed exp": "0xbe00",
		"special exp": "0xbe00",
		"dvs": "0x7c7c"
	},{
		"level": 50,
		"species": "Vaporeon",
		"item": "Bright Powder",
		"move1": "Double Team",
		"move2": "Baton Pass",
		"move3": "Surf",
		"move4": "Ice Beam",
		"unknown2": "0xcf",
		"unknown3": "0x80",
		"hp exp": "0xbe00",
		"attack exp": "0xbe00",
		"defense exp": "0xbe00",
		"speed exp": "0xbe00",
		"special exp": "0xbe00",
		"dvs": "0x8c7c"
	},{
		"level": 50,
		"species": "Forretress",
		"item": "Scope Lens",
		"move1": "Swagger",
		"move2": "Spikes",
		"move3": "Sandstorm",
		"move4": "Double-Edge",
		"unknown2": "0xc3",
		"unknown3": "0x80",
		"hp exp": "0xbe00",
		"attack exp": "0xbe00",
		"defense exp": "0xbe00",
		"speed exp": "0xbe00",
		"special exp": "0xbe00",
		"dvs": "0x8c7c"
	},{
		"level": 50,
		"species": "Girafarig",
		"item": "Miracleberry",
		"move1": "Double Team",
		"move2": "Baton Pass",
		"move3": "Psychic",
		"move4": "Crunch",
		"unknown2": "0xcf",
		"unknown3": "0x80",
		"hp exp": "0xbe00",
		"attack exp": "0xbe00",
		"defense exp": "0xbe00",
		"speed exp": "0xbe00",
		"special exp": "0xbe00",
		"dvs": "0x7c7c"
	}]
}]