[{
	"group": "Pokémon Trainer",
	"trainer": "Student",
	"text": "text/cal.txt",
	"pokemon": [{
		"level": 50,
		"species": "Pikachu",
		"item": "Light Ball",
		"move1": "Thunderbolt",
		"happiness": "0x7f",
		"hp exp": "0x0000",
		"attack exp": "0x0000",
		"defense exp": "0x0000",
		"speed exp": "0xffff",
		"special exp": "0xffff",
		"dvs": "0xeeff"
	},{
		"level": 50,
		"species": "Raichu",
		"item": "Stick",
		"move1": "Thunderbolt",
		"happiness": "0x7f",
		"hp exp": "0x0000",
		"attack exp": "0x0000",
		"defense exp": "0x0000",
		"speed exp": "0xffff",
		"special exp": "0x3e80",
		"dvs": "0xe6e0"
	},{
		"level": 50,
		"species": "Sandslash",
		"item": "Metal Powder",
		"move1": "Earthquake",
		"happiness": "0x7f",
		"hp exp": "0x0000",
		"attack exp": "0x0000",
		"defense exp": "0x0000",
		"speed exp": "0x0000",
		"special exp": "0x0000",
		"dvs": "0x0000"
	},{
		"level": 50,
		"species": "Cubone",
		"item": "Thick Club",
		"move1": "Earthquake",
		"happiness": "0x7f",
		"hp exp": "0x0000",
		"attack exp": "0xa410",
		"defense exp": "0x0000",
		"speed exp": "0xffff",
		"special exp": "0x0000",
		"dvs": "0xe0ff"
	},{
		"level": 50,
		"species": "Marowak",
		"item": "Lucky Punch",
		"move1": "Earthquake",
		"happiness": "0x7f",
		"hp exp": "0x0000",
		"attack exp": "0x1770",
		"defense exp": "0x0000",
		"speed exp": "0xffff",
		"special exp": "0x0000",
		"dvs": "0x60ee"
	},{
		"level": 50,
		"species": "Shuckle",
		"item": "Focus Band",
		"move1": "Withdraw",
		"unknown2": "0xc0",
		"happiness": "0x7f",
		"hp exp": "0xffff",
		"attack exp": "0x0000",
		"defense exp": "0xffff",
		"speed exp": "0xffff",
		"special exp": "0xffff",
		"dvs": "0x0fff"
	}]
},{
	"group": "Cooltrainer♂",
	"trainer": "Connor",
	"unknown1": "0x47",
	"text": "text/academy/skilltest/elitefour/connor.txt",
	"pokemon": [{
		"level": 80,
		"species": "Gyarados",
		"move1": "Hyper Beam",
		"unknown2": "0xc0",
		"happiness": "0x7f",
		"hp exp": "0x1f40",
		"attack exp": "0x0000",
		"defense exp": "0x0000",
		"speed exp": "0x0000",
		"special exp": "0x0000",
		"dvs": "0x0600"
	},{
		"level": 60,
		"species": "Remoraid",
		"move1": "Hyper Beam",
		"unknown2": "0xc0",
		"happiness": "0x7f",
		"hp exp": "0xffff",
		"attack exp": "0xffff",
		"defense exp": "0x0000",
		"speed exp": "0x0000",
		"special exp": "0xffff",
		"dvs": "0xffff"
	},{
		"level": 60,
		"species": "Muk",
		"move1": "Hyper Beam",
		"unknown2": "0xc0",
		"happiness": "0x7f",
		"hp exp": "0x0000",
		"attack exp": "0x0000",
		"defense exp": "0x0000",
		"speed exp": "0x0000",
		"special exp": "0x0000",
		"dvs": "0x0000"
	},{
		"level": 60,
		"species": "Seadra",
		"move1": "Hyper Beam",
		"unknown2": "0xc0",
		"happiness": "0x7f",
		"hp exp": "0xffff",
		"attack exp": "0xffff",
		"defense exp": "0x0000",
		"speed exp": "0x0000",
		"special exp": "0x0fa0",
		"dvs": "0xf11f"
	},{
		"level": 60,
		"species": "Kingler",
		"move1": "Hyper Beam",
		"unknown2": "0xc0",
		"happiness": "0x7f",
		"hp exp": "0xffff",
		"attack exp": "0xffff",
		"defense exp": "0x0000",
		"speed exp": "0x0000",
		"special exp": "0x2710",
		"dvs": "0xf11f"
	},{
		"level": 80,
		"species": "Magcargo",
		"move1": "Hyper Beam",
		"unknown2": "0xc0",
		"happiness": "0x7f",
		"hp exp": "0x3a98",
		"attack exp": "0xffff",
		"defense exp": "0x0000",
		"speed exp": "0x2ee0",
		"special exp": "0x0000",
		"dvs": "0xf011"
	}]
},{
	"group": "Pokémon Trainer",
	"trainer": "Student",
	"text": "text/cal.txt",
	"pokemon": [{
		"level": 50,
		"species": "Furret",
		"move1": "Endure",
		"move2": "Reversal",
		"move3": "Focus Energy",
		"happiness": "0x7f",
		"hp exp": "0x07d0",
		"attack exp": "0xffff",
		"defense exp": "0x0000",
		"speed exp": "0x0000",
		"special exp": "0x0000",
		"dvs": "0xe000"
	},{
		"level": 50,
		"species": "Scyther",
		"move1": "Endure",
		"move2": "Reversal",
		"move3": "Agility",
		"happiness": "0xc8",
		"hp exp": "0x0000",
		"attack exp": "0x0258",
		"defense exp": "0x0000",
		"speed exp": "0x0000",
		"special exp": "0x0000",
		"dvs": "0x6000"
	},{
		"level": 50,
		"species": "Raticate",
		"move1": "Endure",
		"move2": "Reversal",
		"move3": "Icy Wind",
		"happiness": "0x7f",
		"hp exp": "0x07d0",
		"attack exp": "0xea60",
		"defense exp": "0x0000",
		"speed exp": "0x0d48",
		"special exp": "0x0000",
		"dvs": "0xa000"
	},{
		"level": 50,
		"species": "Houndoom",
		"move1": "Endure",
		"move2": "Reversal",
		"happiness": "0xb1",
		"hp exp": "0x0ed8",
		"attack exp": "0x7d00",
		"defense exp": "0x07d0",
		"speed exp": "0x0014",
		"special exp": "0x0000",
		"dvs": "0x8000"
	},{
		"level": 50,
		"species": "Raichu",
		"move1": "Endure",
		"move2": "Reversal",
		"move3": "Agility",
		"happiness": "0x7f",
		"hp exp": "0x0000",
		"attack exp": "0x9c40",
		"defense exp": "0x2ee0",
		"speed exp": "0x0000",
		"special exp": "0x0000",
		"dvs": "0x6111"
	},{
		"level": 50,
		"species": "Typhlosion",
		"move1": "Endure",
		"move2": "Reversal",
		"move3": "Foresight",
		"happiness": "0x7f",
		"hp exp": "0x03e8",
		"attack exp": "0xffff",
		"defense exp": "0x0000",
		"speed exp": "0x0000",
		"special exp": "0x0000",
		"dvs": "0x1000"
	}]
},{
	"group": "Cooltrainer♀",
	"trainer": "Becky",
	"unknown1": "0x48",
	"text": "text/academy/skilltest/elitefour/becky.txt",
	"pokemon": [{
		"level": 55,
		"species": "Machamp",
		"move1": "Meditate",
		"move2": "Hyper Beam",
		"unknown2": "0x30",
		"happiness": "0xc8",
		"hp exp": "0x03e8",
		"attack exp": "0x6590",
		"defense exp": "0x23f0",
		"speed exp": "0xffff",
		"special exp": "0x0000",
		"dvs": "0x08e0"
	},{
		"level": 55,
		"species": "Electabuzz",
		"move1": "Meditate",
		"move2": "Hyper Beam",
		"unknown2": "0x30",
		"happiness": "0xc8",
		"hp exp": "0x4e20",
		"attack exp": "0xea60",
		"defense exp": "0xdac0",
		"speed exp": "0x0000",
		"special exp": "0x0000",
		"dvs": "0xfe00"
	},{
		"level": 55,
		"species": "Scizor",
		"move1": "Swords Dance",
		"move2": "Hyper Beam",
		"unknown2": "0x30",
		"happiness": "0xc8",
		"hp exp": "0x6978",
		"attack exp": "0x7530",
		"defense exp": "0x0000",
		"speed exp": "0x7530",
		"special exp": "0x0000",
		"dvs": "0x00e0"
	},{
		"level": 55,
		"species": "Bellossom",
		"move1": "Swords Dance",
		"move2": "Hyper Beam",
		"unknown2": "0x30",
		"happiness": "0xc8",
		"hp exp": "0x07d0",
		"attack exp": "0xffff",
		"defense exp": "0x3e80",
		"speed exp": "0xffff",
		"special exp": "0x0000",
		"dvs": "0xf0f0"
	},{
		"level": 55,
		"species": "Primeape",
		"move1": "Meditate",
		"move2": "Hyper Beam",
		"unknown2": "0x30",
		"happiness": "0xc8",
		"hp exp": "0x9c40",
		"attack exp": "0xffff",
		"defense exp": "0xea60",
		"speed exp": "0x0640",
		"special exp": "0x0000",
		"dvs": "0xea00"
	},{
		"level": 55,
		"species": "Pinsir",
		"move1": "Swords Dance",
		"move2": "Hyper Beam",
		"unknown2": "0x30",
		"happiness": "0xc8",
		"hp exp": "0x1f40",
		"attack exp": "0xa410",
		"defense exp": "0x0000",
		"speed exp": "0x3e80",
		"special exp": "0x0000",
		"dvs": "0x0000"
	}]
},{
	"group": "Pokémon Trainer",
	"trainer": "Student",
	"text": "text/cal.txt",
	"pokemon": [{
		"level": 50,
		"species": "Poliwrath",
		"move1": "Mind Reader",
		"move2": "Dynamicpunch",
		"happiness": "0x7f",
		"hp exp": "0x2710",
		"attack exp": "0x1f40",
		"defense exp": "0x0000",
		"speed exp": "0xfa00",
		"special exp": "0x01f4",
		"dvs": "0x6000"
	},{
		"level": 50,
		"species": "Pineco",
		"move1": "Bide",
		"move2": "Rollout",
		"happiness": "0x7f",
		"hp exp": "0xcb20",
		"attack exp": "0x9c40",
		"defense exp": "0x0000",
		"speed exp": "0x0000",
		"special exp": "0xa7f8",
		"dvs": "0xf16e"
	},{
		"level": 50,
		"species": "Hitmonlee",
		"move1": "Foresight",
		"move2": "Dynamicpunch",
		"happiness": "0x7f",
		"hp exp": "0x1f40",
		"attack exp": "0x0000",
		"defense exp": "0x5dc0",
		"speed exp": "0x7530",
		"special exp": "0x0000",
		"dvs": "0x0d77"
	},{
		"level": 50,
		"species": "Golem",
		"move1": "Defense Curl",
		"move2": "Rollout",
		"happiness": "0x7f",
		"hp exp": "0x2710",
		"attack exp": "0x0000",
		"defense exp": "0x0000",
		"speed exp": "0x0000",
		"special exp": "0x8ca0",
		"dvs": "0x11ff"
	},{
		"level": 50,
		"species": "Rhydon",
		"move1": "Swagger",
		"move2": "Roar",
		"move3": "Fury Cutter",
		"happiness": "0x7f",
		"hp exp": "0x0000",
		"attack exp": "0x07d0",
		"defense exp": "0x0000",
		"speed exp": "0x0000",
		"special exp": "0x0000",
		"dvs": "0x6077"
	},{
		"level": 50,
		"species": "Steelix",
		"move1": "Toxic",
		"move2": "Bind",
		"move3": "Rage",
		"happiness": "0x7f",
		"hp exp": "0x07d0",
		"attack exp": "0x9c40",
		"defense exp": "0x06a4",
		"speed exp": "0x6720",
		"special exp": "0xd8ef",
		"dvs": "0xa08e"
	}]
},{
	"group": "Juggler",
	"trainer": "Ferris",
	"unknown1": "0x49",
	"text": "text/academy/skilltest/elitefour/ferris.txt",
	"pokemon": [{
		"level": 55,
		"species": "Dragonite",
		"move1": "Wing Attack",
		"happiness": "0x7f",
		"hp exp": "0x1770",
		"attack exp": "0x0000",
		"defense exp": "0x0000",
		"speed exp": "0x0000",
		"special exp": "0x0000",
		"dvs": "0x0000"
	},{
		"level": 50,
		"species": "Arcanine",
		"move1": "Flamethrower",
		"move2": "Extremespeed",
		"happiness": "0x7f",
		"hp exp": "0x0000",
		"attack exp": "0x0000",
		"defense exp": "0x0000",
		"speed exp": "0x0000",
		"special exp": "0x07d0",
		"dvs": "0x0442"
	},{
		"level": 50,
		"species": "Flareon",
		"move1": "Flamethrower",
		"move2": "Quick Attack",
		"happiness": "0x7f",
		"hp exp": "0x3e80",
		"attack exp": "0x0000",
		"defense exp": "0x32c8",
		"speed exp": "0xea60",
		"special exp": "0x0000",
		"dvs": "0x6606"
	},{
		"level": 50,
		"species": "Magmar",
		"move1": "Flamethrower",
		"move2": "Fire Punch",
		"happiness": "0x7f",
		"hp exp": "0x2328",
		"attack exp": "0x0000",
		"defense exp": "0x2ee0",
		"speed exp": "0x0000",
		"special exp": "0x0000",
		"dvs": "0x0743"
	},{
		"level": 50,
		"species": "Typhlosion",
		"move1": "Flamethrower",
		"move2": "Fire Punch",
		"happiness": "0x7f",
		"hp exp": "0x0000",
		"attack exp": "0x0000",
		"defense exp": "0x0000",
		"speed exp": "0x0000",
		"special exp": "0x0000",
		"dvs": "0xf000"
	},{
		"level": 55,
		"species": "Tyranitar",
		"move1": "Rock Slide",
		"move2": "Surf",
		"happiness": "0x7f",
		"hp exp": "0xffff",
		"attack exp": "0x0000",
		"defense exp": "0xffff",
		"speed exp": "0x0000",
		"special exp": "0x07d0",
		"dvs": "0x7f11"
	}]
},{
	"group": "Pokémon Trainer",
	"trainer": "Student",
	"text": "text/cal.txt",
	"pokemon": [{
		"level": 50,
		"species": "Gyarados",
		"move1": "Surf",
		"move2": "Sandstorm",
		"happiness": "0x7f",
		"hp exp": "0x0bb8",
		"attack exp": "0x0000",
		"defense exp": "0x0000",
		"speed exp": "0x0000",
		"special exp": "0x0000",
		"dvs": "0x0777"
	},{
		"level": 50,
		"species": "Exeggutor",
		"move1": "Stomp",
		"move2": "Synthesis",
		"move3": "Sunny Day",
		"happiness": "0x7f",
		"hp exp": "0x0000",
		"attack exp": "0xea60",
		"defense exp": "0x0000",
		"speed exp": "0xffff",
		"special exp": "0x0000",
		"dvs": "0x80e0"
	},{
		"level": 50,
		"species": "Magmar",
		"move1": "Flamethrower",
		"move2": "Barrier",
		"happiness": "0x7f",
		"hp exp": "0x9c40",
		"attack exp": "0x0000",
		"defense exp": "0x04b0",
		"speed exp": "0x0000",
		"special exp": "0x0000",
		"dvs": "0x0660"
	},{
		"level": 50,
		"species": "Houndoom",
		"move1": "Flamethrower",
		"move2": "Solarbeam",
		"move3": "Sunny Day",
		"happiness": "0x7f",
		"hp exp": "0x9470",
		"attack exp": "0x0000",
		"defense exp": "0x0000",
		"speed exp": "0xc350",
		"special exp": "0x0578",
		"dvs": "0x6771"
	},{
		"level": 50,
		"species": "Jumpluff",
		"move1": "Solarbeam",
		"move2": "Sunny Day",
		"happiness": "0x7f",
		"hp exp": "0x2ee0",
		"attack exp": "0x0000",
		"defense exp": "0x0000",
		"speed exp": "0xffff",
		"special exp": "0x0fa0",
		"dvs": "0x00e4"
	},{
		"level": 50,
		"species": "Dodrio",
		"move1": "Fury Attack",
		"move2": "Fly",
		"happiness": "0x7f",
		"hp exp": "0xfa00",
		"attack exp": "0x0320",
		"defense exp": "0x0000",
		"speed exp": "0x3e80",
		"special exp": "0x0000",
		"dvs": "0x0663"
	}]
},{
	"group": "Swimmer♀",
	"trainer": "Julian",
	"unknown1": "0x4a",
	"text": "text/academy/skilltest/elitefour/julian.txt",
	"pokemon": [{
		"level": 55,
		"species": "Starmie",
		"move1": "Minimize",
		"move2": "Rain Dance",
		"move3": "Thunder",
		"happiness": "0x7f",
		"hp exp": "0xffff",
		"attack exp": "0x0000",
		"defense exp": "0x00c8",
		"speed exp": "0x0000",
		"special exp": "0x1770",
		"dvs": "0x3115"
	},{
		"level": 50,
		"species": "Slowbro",
		"move1": "Surf",
		"happiness": "0x7f",
		"hp exp": "0x0000",
		"attack exp": "0x0000",
		"defense exp": "0x0000",
		"speed exp": "0x0000",
		"special exp": "0x0000",
		"dvs": "0x0000"
	},{
		"level": 50,
		"species": "Kingdra",
		"move1": "Twister",
		"move2": "Surf",
		"happiness": "0x7f",
		"hp exp": "0x07d0",
		"attack exp": "0x0000",
		"defense exp": "0x0000",
		"speed exp": "0x0000",
		"special exp": "0x0000",
		"dvs": "0x0000"
	},{
		"level": 50,
		"species": "Golduck",
		"move1": "Surf",
		"happiness": "0x7f",
		"hp exp": "0x1f40",
		"attack exp": "0x0000",
		"defense exp": "0x0000",
		"speed exp": "0x0000",
		"special exp": "0x0000",
		"dvs": "0x0000"
	},{
		"level": 50,
		"species": "Octillery",
		"move1": "Surf",
		"happiness": "0x7f",
		"hp exp": "0x0000",
		"attack exp": "0x0000",
		"defense exp": "0x0000",
		"speed exp": "0x0000",
		"special exp": "0x0000",
		"dvs": "0x0000"
	},{
		"level": 55,
		"species": "Staryu",
		"move1": "Minimize",
		"move2": "Rain Dance",
		"move3": "Thunder",
		"happiness": "0x7f",
		"hp exp": "0xffff",
		"attack exp": "0x0000",
		"defense exp": "0x3e80",
		"speed exp": "0x4e20",
		"special exp": "0xbf68",
		"dvs": "0xff1f"
	}]
}]
