[{
	"group": "Gym Leader",
	"trainer": "Blue",
	"unknown1": "0xae",
	"text": "text/gymleadercastle/kanto/blue2.txt",
	"pokemon": [{
		"level": 50,
		"species": "Scyther",
		"item": "Bright Powder",
		"move1": "Swords Dance",
		"move2": "Agility",
		"move3": "Baton Pass",
		"move4": "Wing Attack",
		"happiness": "0x80",
		"hp exp": "0xc800",
		"attack exp": "0xc800",
		"defense exp": "0xc800",
		"speed exp": "0xc800",
		"special exp": "0xc800",
		"dvs": "0xda9a"
	},{
		"level": 50,
		"species": "Miltank",
		"item": "Miracleberry",
		"move1": "Body Slam",
		"move2": "Earthquake",
		"move3": "Reversal",
		"move4": "Shadow Ball",
		"happiness": "0x80",
		"hp exp": "0xc800",
		"attack exp": "0xc800",
		"defense exp": "0xc800",
		"speed exp": "0xc800",
		"special exp": "0xc800",
		"dvs": "0x9a9a"
	},{
		"level": 50,
		"species": "Gengar",
		"item": "King's Rock",
		"move1": "Psychic",
		"move2": "Ice Punch",
		"move3": "Fire Punch",
		"move4": "Thunderbolt",
		"happiness": "0x80",
		"hp exp": "0xc800",
		"attack exp": "0xc800",
		"defense exp": "0xc800",
		"speed exp": "0xc800",
		"special exp": "0xc800",
		"dvs": "0x9a9a"
	},{
		"level": 50,
		"species": "Houndoom",
		"item": "Focus Band",
		"move1": "Flamethrower",
		"move2": "Crunch",
		"move3": "Iron Tail",
		"move4": "Reversal",
		"happiness": "0x80",
		"hp exp": "0xc800",
		"attack exp": "0xc800",
		"defense exp": "0xc800",
		"speed exp": "0xc800",
		"special exp": "0xc800",
		"dvs": "0x9a9a"
	},{
		"level": 50,
		"species": "Piloswine",
		"item": "Quick Claw",
		"move1": "Ice Beam",
		"move2": "Earthquake",
		"move3": "Rock Slide",
		"move4": "Roar",
		"happiness": "0x80",
		"hp exp": "0xc800",
		"attack exp": "0xc800",
		"defense exp": "0xc800",
		"speed exp": "0xc800",
		"special exp": "0xc800",
		"dvs": "0xca9d"
	},{
		"level": 50,
		"species": "Kingdra",
		"item": "Scope Lens",
		"move1": "Surf",
		"move2": "Dragonbreath",
		"move3": "Ice Beam",
		"move4": "Flail",
		"happiness": "0x80",
		"hp exp": "0xc800",
		"attack exp": "0xc800",
		"defense exp": "0xc800",
		"speed exp": "0xc800",
		"special exp": "0xc800",
		"dvs": "0x7a9a"
	}]
}]
